Workbook

Sheet README
A1: Fuel Shock Stress Test: unit economics and shock engine
A3: Question: what happens to a trucking operator's margin and cash position when crude oil spikes,
A4: and what price increase restores profitability?
A6: Sheets:
A7: Inputs: per-country baseline assumptions. ALL VALUES ARE v0 ESTIMATES pending calibration.
A8: UnitEconomics: per-km cost stack, baseline EBIT margin, fuel share of revenue (live formulas).
A9: ShockEngine: single-scenario stress test with adjustable shock, duration, pass-through, lag.
A10: SurvivalGrid: margin outcome across shock magnitude x duration for a selected country.
A12: Yellow cells are user inputs. Everything else is calculated.
A13: Generated by excel/build_model.py. Safe to edit in Excel; regenerate to reset.

Sheet Inputs
A1: Baseline assumptions per country (v0 estimates, to be calibrated)
A3: Parameter | B3: Unit | C3: US | D3: India | E3: China | F3: Germany | G3: Brazil | H3: Source / calibration plan
A4: Diesel pump price | B4: USD per liter | C4: 0.95 | D4: 1.08 | E4: 1.05 | F4: 1.8 | G4: 1.1 | H4: v0 estimate. Calibrate: EIA (US), PPAC (India), NDRC (China), Eurostat (Germany), ANP (Brazil)
A5: Crude-to-pump beta | B5: pct of crude move passed to pump | C5: 0.9 | D5: 0.5 | E5: 0.6 | F5: 0.45 | G5: 0.65 | H5: v0 estimate of tax wedge. Calibrate by regressing pump on crude, 2015 to 2025
A6: Fuel efficiency | B6: km per liter | C6: 2.8 | D6: 4 | E6: 3 | F6: 3 | G6: 2.9 | H6: v0 estimate. US class 8 approx 6.5 mpg; lighter fleet mix in India
A7: Annual distance | B7: km per truck per year | C7: 160000 | D7: 100000 | E7: 120000 | F7: 130000 | G7: 110000 | H7: v0 estimate. Industry utilization benchmarks
A8: Driver wage incl employer costs | B8: USD per month | C8: 5000 | D8: 380 | E8: 1250 | F8: 4400 | G8: 700 | H8: v0 estimate. Calibrate: BLS OES (US), Eurostat (DE, incl social charges), industry reports (IN, CN, BR)
A9: Drivers per truck | B9: ratio | C9: 1.1 | D9: 1.2 | E9: 1.1 | F9: 1.1 | G9: 1.1 | H9: v0 estimate, accounts for relief drivers and turnover
A10: Maintenance and tires | B10: USD per km | C10: 0.12 | D10: 0.05 | E10: 0.07 | F10: 0.11 | G10: 0.07 | H10: v0 estimate. ATRI ops cost survey (US) as anchor
A11: Tolls and fees | B11: USD per km | C11: 0.04 | D11: 0.03 | E11: 0.1 | F11: 0.15 | G11: 0.04 | H11: v0 estimate. Germany Maut and China expressway tolls are major cost lines
A12: Insurance and permits | B12: USD per truck per year | C12: 12000 | D12: 2500 | E12: 4000 | F12: 9000 | G12: 3500 | H12: v0 estimate
A13: Financing and depreciation | B13: USD per truck per year | C13: 28000 | D13: 6000 | E13: 10000 | F13: 24000 | G13: 11000 | H13: v0 estimate. New tractor cost amortized approx 7 years; cheaper vehicles in IN, CN
A14: Overhead share of revenue | B14: pct | C14: 0.08 | D14: 0.07 | E14: 0.07 | F14: 0.08 | G14: 0.08 | H14: v0 estimate: admin, dispatch, facilities
A15: Revenue per km | B15: USD per km | C15: 1.4 | D15: 0.58 | E15: 0.9 | F15: 1.85 | G15: 0.82 | H15: v0 estimate calibrated so baseline margins land in the realistic 4 to 9 pct trucking band
A16: Cash buffer | B16: months of operating cost | C16: 2.5 | D16: 1.5 | E16: 2 | F16: 3 | G16: 1.5 | H16: v0 estimate by market maturity. Calibrate from CIQ cash and cost data

Sheet UnitEconomics
A1: Per-km unit economics (all formulas reference Inputs)
A3: Line item (USD per km) | B3: US | C3: India | D3: China | E3: Germany | F3: Brazil
A4: Fuel | B4: =Inputs!C4/Inputs!C6 | C4: =Inputs!D4/Inputs!D6 | D4: =Inputs!E4/Inputs!E6 | E4: =Inputs!F4/Inputs!F6 | F4: =Inputs!G4/Inputs!G6
A5: Driver wages | B5: =Inputs!C8*12*Inputs!C9/Inputs!C7 | C5: =Inputs!D8*12*Inputs!D9/Inputs!D7 | D5: =Inputs!E8*12*Inputs!E9/Inputs!E7 | E5: =Inputs!F8*12*Inputs!F9/Inputs!F7 | F5: =Inputs!G8*12*Inputs!G9/Inputs!G7
A6: Maintenance and tires | B6: =Inputs!C10 | C6: =Inputs!D10 | D6: =Inputs!E10 | E6: =Inputs!F10 | F6: =Inputs!G10
A7: Tolls and fees | B7: =Inputs!C11 | C7: =Inputs!D11 | D7: =Inputs!E11 | E7: =Inputs!F11 | F7: =Inputs!G11
A8: Insurance and permits | B8: =Inputs!C12/Inputs!C7 | C8: =Inputs!D12/Inputs!D7 | D8: =Inputs!E12/Inputs!E7 | E8: =Inputs!F12/Inputs!F7 | F8: =Inputs!G12/Inputs!G7
A9: Financing and depreciation | B9: =Inputs!C13/Inputs!C7 | C9: =Inputs!D13/Inputs!D7 | D9: =Inputs!E13/Inputs!E7 | E9: =Inputs!F13/Inputs!F7 | F9: =Inputs!G13/Inputs!G7
A10: Overhead | B10: =Inputs!C14*Inputs!C15 | C10: =Inputs!D14*Inputs!D15 | D10: =Inputs!E14*Inputs!E15 | E10: =Inputs!F14*Inputs!F15 | F10: =Inputs!G14*Inputs!G15
A11: Total cost per km | B11: =SUM(B4:B10) | C11: =SUM(C4:C10) | D11: =SUM(D4:D10) | E11: =SUM(E4:E10) | F11: =SUM(F4:F10)
A12: Revenue per km | B12: =Inputs!C15 | C12: =Inputs!D15 | D12: =Inputs!E15 | E12: =Inputs!F15 | F12: =Inputs!G15
A13: EBIT per km | B13: =B12-B11 | C13: =C12-C11 | D13: =D12-D11 | E13: =E12-E11 | F13: =F12-F11
A14: EBIT margin | B14: =B13/B12 | C14: =C13/C12 | D14: =D13/D12 | E14: =E13/E12 | F14: =F13/F12
A15: Fuel share of revenue | B15: =B4/B12 | C15: =C4/C12 | D15: =D4/D12 | E15: =E4/E12 | F15: =F4/F12
A16: Fuel share of total cost | B16: =B4/B11 | C16: =C4/C11 | D16: =D4/D11 | E16: =E4/E11 | F16: =F4/F11

Sheet ShockEngine
A1: Shock scenario engine (yellow = your levers)
A3: Crude shock | B3: 0.5 | C3: pct increase in crude, e.g. 0.5 = +50%
A4: Duration | B4: 6 | C4: months the spike lasts
A5: Pass-through | B5: 0.5 | C5: share of fuel increase recovered via surcharge, steady state
A6: Surcharge lag | B6: 2 | C6: months before surcharges kick in
A8: Metric | B8: US | C8: India | D8: China | E8: Germany | F8: Brazil
A9: Pump price shock | B9: =$B$3*Inputs!C5 | C9: =$B$3*Inputs!D5 | D9: =$B$3*Inputs!E5 | E9: =$B$3*Inputs!F5 | F9: =$B$3*Inputs!G5
A10: Effective pass-through | B10: =$B$5*MAX(0,($B$4-$B$6)/$B$4) | C10: =$B$5*MAX(0,($B$4-$B$6)/$B$4) | D10: =$B$5*MAX(0,($B$4-$B$6)/$B$4) | E10: =$B$5*MAX(0,($B$4-$B$6)/$B$4) | F10: =$B$5*MAX(0,($B$4-$B$6)/$B$4)
A11: Margin hit (pp of revenue) | B11: =UnitEconomics!B15*B9*(1-B10) | C11: =UnitEconomics!C15*C9*(1-C10) | D11: =UnitEconomics!D15*D9*(1-D10) | E11: =UnitEconomics!E15*E9*(1-E10) | F11: =UnitEconomics!F15*F9*(1-F10)
A12: Shocked EBIT margin | B12: =UnitEconomics!B14-B11 | C12: =UnitEconomics!C14-C11 | D12: =UnitEconomics!D14-D11 | E12: =UnitEconomics!E14-E11 | F12: =UnitEconomics!F14-F11
A13: Monthly burn if negative (USD/truck) | B13: =MAX(0,-B12)*Inputs!C15*Inputs!C7/12 | C13: =MAX(0,-C12)*Inputs!D15*Inputs!D7/12 | D13: =MAX(0,-D12)*Inputs!E15*Inputs!E7/12 | E13: =MAX(0,-E12)*Inputs!F15*Inputs!F7/12 | F13: =MAX(0,-F12)*Inputs!G15*Inputs!G7/12
A14: Cash available (USD/truck) | B14: =Inputs!C16*UnitEconomics!B11*Inputs!C7/12 | C14: =Inputs!D16*UnitEconomics!C11*Inputs!D7/12 | D14: =Inputs!E16*UnitEconomics!D11*Inputs!E7/12 | E14: =Inputs!F16*UnitEconomics!E11*Inputs!F7/12 | F14: =Inputs!G16*UnitEconomics!F11*Inputs!G7/12
A15: Months to cash breach | B15: =IF(B12>=0,"survives",IF(B13=0,"survives",B14/B13)) | C15: =IF(C12>=0,"survives",IF(C13=0,"survives",C14/C13)) | D15: =IF(D12>=0,"survives",IF(D13=0,"survives",D14/D13)) | E15: =IF(E12>=0,"survives",IF(E13=0,"survives",E14/E13)) | F15: =IF(F12>=0,"survives",IF(F13=0,"survives",F14/F13))
A16: Price increase to restore margin | B16: =B11 | C16: =C11 | D16: =D11 | E16: =E11 | F16: =F11
A18: Note: price increase to restore margin equals the unrecovered fuel hit as a share of revenue; assumes volumes hold, which is the next refinement (demand elasticity).

Sheet SurvivalGrid
A1: Shocked EBIT margin: crude shock magnitude x duration
A3: Country (1=US 2=India 3=China 4=Germany 5=Brazil) | F3: 1
A4: Pass-through | F4: 0.5
A5: Surcharge lag (months) | F5: 2
A7: Crude shock \ Duration (months) | B7: 3 | C7: 6 | D7: 9 | E7: 12
A8: 0.1 | B8: =INDEX(UnitEconomics!$B$14:$F$14,$F$3)-INDEX(UnitEconomics!$B$15:$F$15,$F$3)*$A8*INDEX(Inputs!$C$5:$G$5,$F$3)*(1-$F$4*MAX(0,(B$7-$F$5)/B$7)) | C8: =INDEX(UnitEconomics!$B$14:$F$14,$F$3)-INDEX(UnitEconomics!$B$15:$F$15,$F$3)*$A8*INDEX(Inputs!$C$5:$G$5,$F$3)*(1-$F$4*MAX(0,(C$7-$F$5)/C$7)) | D8: =INDEX(UnitEconomics!$B$14:$F$14,$F$3)-INDEX(UnitEconomics!$B$15:$F$15,$F$3)*$A8*INDEX(Inputs!$C$5:$G$5,$F$3)*(1-$F$4*MAX(0,(D$7-$F$5)/D$7)) | E8: =INDEX(UnitEconomics!$B$14:$F$14,$F$3)-INDEX(UnitEconomics!$B$15:$F$15,$F$3)*$A8*INDEX(Inputs!$C$5:$G$5,$F$3)*(1-$F$4*MAX(0,(E$7-$F$5)/E$7))
A9: 0.2 | B9: =INDEX(UnitEconomics!$B$14:$F$14,$F$3)-INDEX(UnitEconomics!$B$15:$F$15,$F$3)*$A9*INDEX(Inputs!$C$5:$G$5,$F$3)*(1-$F$4*MAX(0,(B$7-$F$5)/B$7)) | C9: =INDEX(UnitEconomics!$B$14:$F$14,$F$3)-INDEX(UnitEconomics!$B$15:$F$15,$F$3)*$A9*INDEX(Inputs!$C$5:$G$5,$F$3)*(1-$F$4*MAX(0,(C$7-$F$5)/C$7)) | D9: =INDEX(UnitEconomics!$B$14:$F$14,$F$3)-INDEX(UnitEconomics!$B$15:$F$15,$F$3)*$A9*INDEX(Inputs!$C$5:$G$5,$F$3)*(1-$F$4*MAX(0,(D$7-$F$5)/D$7)) | E9: =INDEX(UnitEconomics!$B$14:$F$14,$F$3)-INDEX(UnitEconomics!$B$15:$F$15,$F$3)*$A9*INDEX(Inputs!$C$5:$G$5,$F$3)*(1-$F$4*MAX(0,(E$7-$F$5)/E$7))
A10: 0.3 | B10: =INDEX(UnitEconomics!$B$14:$F$14,$F$3)-INDEX(UnitEconomics!$B$15:$F$15,$F$3)*$A10*INDEX(Inputs!$C$5:$G$5,$F$3)*(1-$F$4*MAX(0,(B$7-$F$5)/B$7)) | C10: =INDEX(UnitEconomics!$B$14:$F$14,$F$3)-INDEX(UnitEconomics!$B$15:$F$15,$F$3)*$A10*INDEX(Inputs!$C$5:$G$5,$F$3)*(1-$F$4*MAX(0,(C$7-$F$5)/C$7)) | D10: =INDEX(UnitEconomics!$B$14:$F$14,$F$3)-INDEX(UnitEconomics!$B$15:$F$15,$F$3)*$A10*INDEX(Inputs!$C$5:$G$5,$F$3)*(1-$F$4*MAX(0,(D$7-$F$5)/D$7)) | E10: =INDEX(UnitEconomics!$B$14:$F$14,$F$3)-INDEX(UnitEconomics!$B$15:$F$15,$F$3)*$A10*INDEX(Inputs!$C$5:$G$5,$F$3)*(1-$F$4*MAX(0,(E$7-$F$5)/E$7))
A11: 0.4 | B11: =INDEX(UnitEconomics!$B$14:$F$14,$F$3)-INDEX(UnitEconomics!$B$15:$F$15,$F$3)*$A11*INDEX(Inputs!$C$5:$G$5,$F$3)*(1-$F$4*MAX(0,(B$7-$F$5)/B$7)) | C11: =INDEX(UnitEconomics!$B$14:$F$14,$F$3)-INDEX(UnitEconomics!$B$15:$F$15,$F$3)*$A11*INDEX(Inputs!$C$5:$G$5,$F$3)*(1-$F$4*MAX(0,(C$7-$F$5)/C$7)) | D11: =INDEX(UnitEconomics!$B$14:$F$14,$F$3)-INDEX(UnitEconomics!$B$15:$F$15,$F$3)*$A11*INDEX(Inputs!$C$5:$G$5,$F$3)*(1-$F$4*MAX(0,(D$7-$F$5)/D$7)) | E11: =INDEX(UnitEconomics!$B$14:$F$14,$F$3)-INDEX(UnitEconomics!$B$15:$F$15,$F$3)*$A11*INDEX(Inputs!$C$5:$G$5,$F$3)*(1-$F$4*MAX(0,(E$7-$F$5)/E$7))
A12: 0.5 | B12: =INDEX(UnitEconomics!$B$14:$F$14,$F$3)-INDEX(UnitEconomics!$B$15:$F$15,$F$3)*$A12*INDEX(Inputs!$C$5:$G$5,$F$3)*(1-$F$4*MAX(0,(B$7-$F$5)/B$7)) | C12: =INDEX(UnitEconomics!$B$14:$F$14,$F$3)-INDEX(UnitEconomics!$B$15:$F$15,$F$3)*$A12*INDEX(Inputs!$C$5:$G$5,$F$3)*(1-$F$4*MAX(0,(C$7-$F$5)/C$7)) | D12: =INDEX(UnitEconomics!$B$14:$F$14,$F$3)-INDEX(UnitEconomics!$B$15:$F$15,$F$3)*$A12*INDEX(Inputs!$C$5:$G$5,$F$3)*(1-$F$4*MAX(0,(D$7-$F$5)/D$7)) | E12: =INDEX(UnitEconomics!$B$14:$F$14,$F$3)-INDEX(UnitEconomics!$B$15:$F$15,$F$3)*$A12*INDEX(Inputs!$C$5:$G$5,$F$3)*(1-$F$4*MAX(0,(E$7-$F$5)/E$7))
A13: 0.75 | B13: =INDEX(UnitEconomics!$B$14:$F$14,$F$3)-INDEX(UnitEconomics!$B$15:$F$15,$F$3)*$A13*INDEX(Inputs!$C$5:$G$5,$F$3)*(1-$F$4*MAX(0,(B$7-$F$5)/B$7)) | C13: =INDEX(UnitEconomics!$B$14:$F$14,$F$3)-INDEX(UnitEconomics!$B$15:$F$15,$F$3)*$A13*INDEX(Inputs!$C$5:$G$5,$F$3)*(1-$F$4*MAX(0,(C$7-$F$5)/C$7)) | D13: =INDEX(UnitEconomics!$B$14:$F$14,$F$3)-INDEX(UnitEconomics!$B$15:$F$15,$F$3)*$A13*INDEX(Inputs!$C$5:$G$5,$F$3)*(1-$F$4*MAX(0,(D$7-$F$5)/D$7)) | E13: =INDEX(UnitEconomics!$B$14:$F$14,$F$3)-INDEX(UnitEconomics!$B$15:$F$15,$F$3)*$A13*INDEX(Inputs!$C$5:$G$5,$F$3)*(1-$F$4*MAX(0,(E$7-$F$5)/E$7))
A14: 1 | B14: =INDEX(UnitEconomics!$B$14:$F$14,$F$3)-INDEX(UnitEconomics!$B$15:$F$15,$F$3)*$A14*INDEX(Inputs!$C$5:$G$5,$F$3)*(1-$F$4*MAX(0,(B$7-$F$5)/B$7)) | C14: =INDEX(UnitEconomics!$B$14:$F$14,$F$3)-INDEX(UnitEconomics!$B$15:$F$15,$F$3)*$A14*INDEX(Inputs!$C$5:$G$5,$F$3)*(1-$F$4*MAX(0,(C$7-$F$5)/C$7)) | D14: =INDEX(UnitEconomics!$B$14:$F$14,$F$3)-INDEX(UnitEconomics!$B$15:$F$15,$F$3)*$A14*INDEX(Inputs!$C$5:$G$5,$F$3)*(1-$F$4*MAX(0,(D$7-$F$5)/D$7)) | E14: =INDEX(UnitEconomics!$B$14:$F$14,$F$3)-INDEX(UnitEconomics!$B$15:$F$15,$F$3)*$A14*INDEX(Inputs!$C$5:$G$5,$F$3)*(1-$F$4*MAX(0,(E$7-$F$5)/E$7))
A16: Red: margin below zero (burning cash). Amber: near breakeven. Green: profitable.
